[
  {
    "id": "0027df96-7599-4699-9ef4-1b2b416c83b6",
    "start": "2025-10-07T15:00:00-05:00",
    "state": "final",
    "service": {
      "id": "d9aa17c2-080c-4747-86df-84962e757150",
      "name": "Tattoo Removal Consultation",
      "color": 8
    },
    "title": "Jessica Braden",
    "end": "2025-10-07T15:30:00-05:00",
    "duration": 30,
    "price": 100.0,
    "client_id": "30222c4b-30f4-4659-a1ac-bb42c622f4c9",
    "staff_id": "52598e4f-6524-455a-a06e-96f2489b29ae",
    "recurring_appointment_id": null,
    "notes": null,
    "appointment_service_id": "58c59f34-e606-494a-8e40-1b5148076e59",
    "service_id": "d9aa17c2-080c-4747-86df-84962e757150",
    "staff_requested": false,
    "finish_duration": 0,
    "post_client_duration": 0,
    "post_staff_duration": 15,
    "base_appointment_service_id": null,
    "client_message": null,
    "guest_number": 0,
    "hex_color": "",
    "effective_tag_ids": [],
    "editable": false,
    "service_option_ids": null,
    "resource_ids": null,
    "abilities": {
      "cancel": false,
      "edit": false,
      "checkout": true
    },
    "is_new_client": true,
    "booked_by_client_full_name": null,
    "origination": "dashboard",
    "className": "theme-12",
    "durationEditable": false
  },
  {
    "id": "0027df96-7599-4699-9ef4-1b2b416c83b6",
    "start": "2025-10-07T15:30:00-05:00",
    "state": "final",
    "service": {
      "id": "e419e52a-8df0-4514-a690-25c128da759a",
      "name": "PIQo Tattoo",
      "color": 12
    },
    "title": "Jessica Braden",
    "end": "2025-10-07T16:15:00-05:00",
    "duration": 45,
    "price": 450.0,
    "client_id": "30222c4b-30f4-4659-a1ac-bb42c622f4c9",
    "staff_id": "52598e4f-6524-455a-a06e-96f2489b29ae",
    "recurring_appointment_id": null,
    "notes": null,
    "appointment_service_id": "e2bae60d-6e41-400f-9c7a-839eeb2c2463",
    "service_id": "e419e52a-8df0-4514-a690-25c128da759a",
    "staff_requested": true,
    "finish_duration": 0,
    "post_client_duration": 0,
    "post_staff_duration": 15,
    "base_appointment_service_id": null,
    "client_message": null,
    "guest_number": 0,
    "hex_color": "",
    "effective_tag_ids": [],
    "editable": false,
    "service_option_ids": null,
    "resource_ids": [
      "e8503e31-e1e9-4f4b-88c4-97d22bf75c16"
    ],
    "abilities": {
      "cancel": false,
      "edit": false,
      "checkout": true
    },
    "is_new_client": true,
    "booked_by_client_full_name": null,
    "origination": "dashboard",
    "className": "theme-12",
    "durationEditable": false
  },
  {
    "id": "0e893c35-feb9-4a3e-bcbc-cc51497446ed",
    "start": "2025-10-10T16:00:00-05:00",
    "state": "final",
    "service": {
      "id": "d32c4998-ff76-445d-a95e-5ca223005dd6",
      "name": "VISIA - Skin Analysis",
      "color": 8
    },
    "title": "Marilyn Gonzalez",
    "end": "2025-10-10T17:00:00-05:00",
    "duration": 60,
    "price": 65.0,
    "client_id": "52ccb88d-51b7-4d84-908f-9efb6e533fd8",
    "staff_id": "52598e4f-6524-455a-a06e-96f2489b29ae",
    "recurring_appointment_id": null,
    "notes": "Paid $65 Consultation fee\nFormer patient, previously under Sarah’s care and on a membership plan, has concerns about hyperpigmentation. She does not recall the specific service she received but is interested in resuming treatments. She is available for late appointments on Thursdays and Fridays due to getting off work at 3:30.",
    "appointment_service_id": "f4dd0908-2f86-4d38-a48d-dc0da3840f37",
    "service_id": "d32c4998-ff76-445d-a95e-5ca223005dd6",
    "staff_requested": false,
    "finish_duration": 0,
    "post_client_duration": 0,
    "post_staff_duration": 15,
    "base_appointment_service_id": null,
    "client_message": null,
    "guest_number": 0,
    "hex_color": "",
    "effective_tag_ids": [],
    "editable": false,
    "service_option_ids": null,
    "resource_ids": null,
    "abilities": {
      "cancel": false,
      "edit": false,
      "checkout": true
    },
    "is_new_client": true,
    "booked_by_client_full_name": null,
    "origination": "dashboard",
    "className": "theme-12",
    "durationEditable": false
  },
  {
    "id": "1e6d97b0-0927-47a9-a777-94bfd06db2c2",
    "start": "2025-10-21T17:45:00-05:00",
    "state": "final",
    "service": {
      "id": "d9aa17c2-080c-4747-86df-84962e757150",
      "name": "Tattoo Removal Consultation",
      "color": 8
    },
    "title": "David Lawson",
    "end": "2025-10-21T18:15:00-05:00",
    "duration": 30,
    "price": 100.0,
    "client_id": "c663001f-0154-4c90-b994-f2f6b4a17c99",
    "staff_id": "52598e4f-6524-455a-a06e-96f2489b29ae",
    "recurring_appointment_id": null,
    "notes": "Tattoo located on left chest 3 inches long\nBlack Ink \nInfinity Sign\nSend Alle Invite",
    "appointment_service_id": "2ce6f2d2-d1bb-4f25-aabb-9be16be1cb5e",
    "service_id": "d9aa17c2-080c-4747-86df-84962e757150",
    "staff_requested": false,
    "finish_duration": 0,
    "post_client_duration": 0,
    "post_staff_duration": 15,
    "base_appointment_service_id": null,
    "client_message": null,
    "guest_number": 0,
    "hex_color": "",
    "effective_tag_ids": [],
    "editable": false,
    "service_option_ids": null,
    "resource_ids": null,
    "abilities": {
      "cancel": false,
      "edit": false,
      "checkout": true
    },
    "is_new_client": true,
    "booked_by_client_full_name": null,
    "origination": "dashboard",
    "className": "theme-12",
    "durationEditable": false
  },
  {
    "id": "1e6d97b0-0927-47a9-a777-94bfd06db2c2",
    "start": "2025-10-21T18:00:00-05:00",
    "state": "final",
    "service": {
      "id": "e419e52a-8df0-4514-a690-25c128da759a",
      "name": "PIQo Tattoo",
      "color": 12
    },
    "title": "David Lawson",
    "end": "2025-10-21T18:45:00-05:00",
    "duration": 45,
    "price": 100.0,
    "client_id": "c663001f-0154-4c90-b994-f2f6b4a17c99",
    "staff_id": "52598e4f-6524-455a-a06e-96f2489b29ae",
    "recurring_appointment_id": null,
    "notes": "Tattoo located on left chest 3 inches long\nBlack Ink \nInfinity Sign\nSend Alle Invite",
    "appointment_service_id": "c979e778-8155-49a7-9403-a2bc5657375a",
    "service_id": "e419e52a-8df0-4514-a690-25c128da759a",
    "staff_requested": true,
    "finish_duration": 0,
    "post_client_duration": 0,
    "post_staff_duration": 15,
    "base_appointment_service_id": null,
    "client_message": null,
    "guest_number": 0,
    "hex_color": "",
    "effective_tag_ids": [],
    "editable": false,
    "service_option_ids": null,
    "resource_ids": [
      "e8503e31-e1e9-4f4b-88c4-97d22bf75c16"
    ],
    "abilities": {
      "cancel": false,
      "edit": false,
      "checkout": true
    },
    "is_new_client": true,
    "booked_by_client_full_name": null,
    "origination": "dashboard",
    "className": "theme-12",
    "durationEditable": false
  },
  {
    "id": "2346aa4f-0664-4818-9ede-c2b420762f71",
    "start": "2025-10-03T10:00:00-05:00",
    "state": "final",
    "service": {
      "id": "153e0f20-e2b3-40ac-90b6-d124abbc2ded",
      "name": "Massage Cupping 90 min",
      "color": 6
    },
    "title": "Chris Flores",
    "end": "2025-10-03T11:45:00-05:00",
    "duration": 105,
    "price": 219.0,
    "client_id": "74f6c27d-b5ce-4287-8663-048d7f457daf",
    "staff_id": "bc0900ae-2e0e-4c1a-bc6f-c3dbafb6b508",
    "recurring_appointment_id": null,
    "notes": "Refer out to Amanda Client interested in NAD+, Weight Loss & Men’s Sexual health",
    "appointment_service_id": "ccf70128-61c0-4bf8-8078-6569f2d05c9f",
    "service_id": "153e0f20-e2b3-40ac-90b6-d124abbc2ded",
    "staff_requested": true,
    "finish_duration": 0,
    "post_client_duration": 0,
    "post_staff_duration": 30,
    "base_appointment_service_id": null,
    "client_message": null,
    "guest_number": 0,
    "hex_color": "",
    "effective_tag_ids": [],
    "editable": false,
    "service_option_ids": null,
    "resource_ids": null,
    "abilities": {
      "cancel": false,
      "edit": false,
      "checkout": true
    },
    "is_new_client": true,
    "booked_by_client_full_name": null,
    "origination": "dashboard",
    "className": "theme-8",
    "durationEditable": false
  },
  {
    "id": "27ec778e-6e13-4975-91c5-51b93192e105",
    "start": "2025-10-10T11:15:00-05:00",
    "state": "final",
    "service": {
      "id": "87a88afb-4597-4346-bb3b-0adb32bb94a5",
      "name": "FB New Clients Only 1 Month Semaglutide/Mounjaro 2.5mg-7.5mg",
      "color": 1
    },
    "title": "Polly Arredondo",
    "end": "2025-10-10T11:45:00-05:00",
    "duration": 30,
    "price": 300.0,
    "client_id": "3609b1f0-11c4-4cf4-a3bd-eaa3f6d9906e",
    "staff_id": "b4b9e43d-8e88-4bb7-89e6-c19baad1ccc1",
    "recurring_appointment_id": null,
    "notes": null,
    "appointment_service_id": "8d42239d-27f4-460f-8db9-7e1abc2152fc",
    "service_id": "87a88afb-4597-4346-bb3b-0adb32bb94a5",
    "staff_requested": false,
    "finish_duration": 0,
    "post_client_duration": 0,
    "post_staff_duration": 15,
    "base_appointment_service_id": null,
    "client_message": null,
    "guest_number": 0,
    "hex_color": "",
    "effective_tag_ids": [],
    "editable": false,
    "service_option_ids": null,
    "resource_ids": null,
    "abilities": {
      "cancel": false,
      "edit": false,
      "checkout": true
    },
    "is_new_client": true,
    "booked_by_client_full_name": null,
    "origination": "sched",
    "className": "theme-10",
    "durationEditable": false
  },
  {
    "id": "3ab6de9f-ad06-4925-86d3-bb45a513a424",
    "start": "2025-10-10T12:30:00-05:00",
    "state": "final",
    "service": {
      "id": "a3f0c51b-e257-49a5-a560-77e6053da938",
      "name": "Neurotoxin (Botox, Dysport)",
      "color": 7
    },
    "title": "Jasmine Ramsey",
    "end": "2025-10-10T13:00:00-05:00",
    "duration": 30,
    "price": 0.0,
    "client_id": "d697dfd9-6988-4de2-8207-82622bc81973",
    "staff_id": "b4b9e43d-8e88-4bb7-89e6-c19baad1ccc1",
    "recurring_appointment_id": null,
    "notes": "Booked online \n$100 in credit\n0 Alle Points",
    "appointment_service_id": "f5ca2476-0ebd-433c-938c-ecf876a7215e",
    "service_id": "a3f0c51b-e257-49a5-a560-77e6053da938",
    "staff_requested": true,
    "finish_duration": 0,
    "post_client_duration": 0,
    "post_staff_duration": 15,
    "base_appointment_service_id": null,
    "client_message": null,
    "guest_number": 0,
    "hex_color": "",
    "effective_tag_ids": [],
    "editable": false,
    "service_option_ids": [
      "5f17fe6c-1168-4d2f-9f74-c470fa4c0671"
    ],
    "resource_ids": null,
    "abilities": {
      "cancel": false,
      "edit": false,
      "checkout": true
    },
    "is_new_client": true,
    "booked_by_client_full_name": "Jasmine Ramsey",
    "origination": "sched_booking_widget",
    "className": "theme-10",
    "durationEditable": false
  },
  {
    "id": "44cd6015-afe5-4dea-a3b1-a1b8592bbe50",
    "start": "2025-10-07T13:15:00-05:00",
    "state": "final",
    "service": {
      "id": "a8552a4a-89af-4dc6-8cdb-adbaeb666534",
      "name": "Sclerotherapy Qtr. Treatment",
      "color": 10
    },
    "title": "Michelle Beene",
    "end": "2025-10-07T14:00:00-05:00",
    "duration": 45,
    "price": 250.0,
    "client_id": "69481ceb-8111-406c-95f2-aab25e9fa0ba",
    "staff_id": "b4b9e43d-8e88-4bb7-89e6-c19baad1ccc1",
    "recurring_appointment_id": null,
    "notes": null,
    "appointment_service_id": "08bf307b-4501-469b-b024-4618b19d67b7",
    "service_id": "a8552a4a-89af-4dc6-8cdb-adbaeb666534",
    "staff_requested": true,
    "finish_duration": 0,
    "post_client_duration": 0,
    "post_staff_duration": 0,
    "base_appointment_service_id": null,
    "client_message": null,
    "guest_number": 0,
    "hex_color": "",
    "effective_tag_ids": [],
    "editable": false,
    "service_option_ids": null,
    "resource_ids": null,
    "abilities": {
      "cancel": false,
      "edit": false,
      "checkout": true
    },
    "is_new_client": true,
    "booked_by_client_full_name": null,
    "origination": "dashboard",
    "className": "theme-10",
    "durationEditable": false
  },
  {
    "id": "46913e43-5304-4dbd-8f68-f41f6669300f",
    "start": "2025-10-16T11:30:00-05:00",
    "state": "final",
    "service": {
      "id": "d32c4998-ff76-445d-a95e-5ca223005dd6",
      "name": "VISIA - Skin Analysis",
      "color": 8
    },
    "title": "Mari Marmolejo",
    "end": "2025-10-16T12:30:00-05:00",
    "duration": 60,
    "price": 100.0,
    "client_id": "06715e14-aca6-4ffc-b764-1b9ba087b53c",
    "staff_id": "6cf098ff-8414-486b-8465-8ce03cb991a1",
    "recurring_appointment_id": null,
    "notes": "She prepaid on GHL for her consultation",
    "appointment_service_id": "e13b218f-c450-4442-aaa8-5200cbb6ddd6",
    "service_id": "d32c4998-ff76-445d-a95e-5ca223005dd6",
    "staff_requested": true,
    "finish_duration": 0,
    "post_client_duration": 0,
    "post_staff_duration": 15,
    "base_appointment_service_id": null,
    "client_message": null,
    "guest_number": 0,
    "hex_color": "",
    "effective_tag_ids": [],
    "editable": false,
    "service_option_ids": null,
    "resource_ids": null,
    "abilities": {
      "cancel": false,
      "edit": false,
      "checkout": true
    },
    "is_new_client": true,
    "booked_by_client_full_name": null,
    "origination": "dashboard",
    "className": "theme-1",
    "durationEditable": false
  },
  {
    "id": "4d84c85e-688c-45ff-801a-0043acdc1785",
    "start": "2025-10-14T17:00:00-05:00",
    "state": "final",
    "service": {
      "id": "7d097d0f-3aed-463e-a793-23c783efb7a4",
      "name": "CO2 Consultation w/ Visia Skin Analysis",
      "color": 8
    },
    "title": "Randee Murphy",
    "end": "2025-10-14T18:00:00-05:00",
    "duration": 60,
    "price": 100.0,
    "client_id": "5dcd2f58-60ae-4fcd-9390-a90eb92b1595",
    "staff_id": "52598e4f-6524-455a-a06e-96f2489b29ae",
    "recurring_appointment_id": null,
    "notes": "Interested in Co2, Hyperpigmentation, PRF/Ez Gel,  Microneedling, LHR & Facial",
    "appointment_service_id": "6cade501-55bc-4e95-b2ab-9fe4d1601d46",
    "service_id": "7d097d0f-3aed-463e-a793-23c783efb7a4",
    "staff_requested": false,
    "finish_duration": 0,
    "post_client_duration": 0,
    "post_staff_duration": 15,
    "base_appointment_service_id": null,
    "client_message": null,
    "guest_number": 0,
    "hex_color": "",
    "effective_tag_ids": [],
    "editable": false,
    "service_option_ids": null,
    "resource_ids": null,
    "abilities": {
      "cancel": false,
      "edit": false,
      "checkout": true
    },
    "is_new_client": true,
    "booked_by_client_full_name": null,
    "origination": "dashboard",
    "className": "theme-12",
    "durationEditable": false
  },
  {
    "id": "5c6a2ad9-0b1b-40af-89d5-0c786cf6bc6e",
    "start": "2025-10-09T14:45:00-05:00",
    "state": "final",
    "service": {
      "id": "a3f0c51b-e257-49a5-a560-77e6053da938",
      "name": "Neurotoxin (Botox, Dysport)",
      "color": 7
    },
    "title": "Nellie Kelley-Schuster",
    "end": "2025-10-09T15:15:00-05:00",
    "duration": 30,
    "price": 832.0,
    "client_id": "2c4f4d72-d3ee-42b9-87eb-b3105e2b67b0",
    "staff_id": "b4b9e43d-8e88-4bb7-89e6-c19baad1ccc1",
    "recurring_appointment_id": null,
    "notes": "0 Alle Points",
    "appointment_service_id": "335758be-dc18-46bb-8d81-9e063507d35a",
    "service_id": "a3f0c51b-e257-49a5-a560-77e6053da938",
    "staff_requested": false,
    "finish_duration": 0,
    "post_client_duration": 0,
    "post_staff_duration": 15,
    "base_appointment_service_id": null,
    "client_message": null,
    "guest_number": 0,
    "hex_color": "",
    "effective_tag_ids": [],
    "editable": false,
    "service_option_ids": [
      "5f17fe6c-1168-4d2f-9f74-c470fa4c0671"
    ],
    "resource_ids": null,
    "abilities": {
      "cancel": false,
      "edit": false,
      "checkout": true
    },
    "is_new_client": true,
    "booked_by_client_full_name": null,
    "origination": "dashboard",
    "className": "theme-10",
    "durationEditable": false
  },
  {
    "id": "5c6a2ad9-0b1b-40af-89d5-0c786cf6bc6e",
    "start": "2025-10-09T13:30:00-05:00",
    "state": "final",
    "service": {
      "id": "d32c4998-ff76-445d-a95e-5ca223005dd6",
      "name": "VISIA - Skin Analysis",
      "color": 8
    },
    "title": "Nellie Kelley-Schuster",
    "end": "2025-10-09T14:15:00-05:00",
    "duration": 45,
    "price": 360.0,
    "client_id": "2c4f4d72-d3ee-42b9-87eb-b3105e2b67b0",
    "staff_id": "52598e4f-6524-455a-a06e-96f2489b29ae",
    "recurring_appointment_id": null,
    "notes": "0 Alle Points",
    "appointment_service_id": "65dbf8c2-4b78-48a7-a24e-192f031a900f",
    "service_id": "d32c4998-ff76-445d-a95e-5ca223005dd6",
    "staff_requested": true,
    "finish_duration": 0,
    "post_client_duration": 0,
    "post_staff_duration": 15,
    "base_appointment_service_id": null,
    "client_message": null,
    "guest_number": 0,
    "hex_color": "",
    "effective_tag_ids": [],
    "editable": false,
    "service_option_ids": null,
    "resource_ids": null,
    "abilities": {
      "cancel": false,
      "edit": false,
      "checkout": true
    },
    "is_new_client": true,
    "booked_by_client_full_name": null,
    "origination": "dashboard",
    "className": "theme-12",
    "durationEditable": false
  },
  {
    "id": "5f0e65a0-f408-4690-a36c-10db39ccc703",
    "start": "2025-10-08T17:00:00-05:00",
    "state": "final",
    "service": {
      "id": "d9aa17c2-080c-4747-86df-84962e757150",
      "name": "Tattoo Removal Consultation",
      "color": 8
    },
    "title": "Hannah Sifuentes",
    "end": "2025-10-08T17:15:00-05:00",
    "duration": 15,
    "price": 100.0,
    "client_id": "86af0fc6-c499-475c-abb4-eab83cf391d5",
    "staff_id": "52598e4f-6524-455a-a06e-96f2489b29ae",
    "recurring_appointment_id": null,
    "notes": "The patient has multiple tattoos and has previously undergone tattoo removal. During her past treatment, she experienced a severe reaction that included blistering and swelling of her arm. She explained that the procedure was performed at a non-credible location. Based on recommendations from friends, she is now seeking treatment in Corpus. The patient resides in Port Lavaca and indicated that evening appointments or Saturdays work best with her schedule. She also mentioned that one of her tattoos was done as a DIY tattoo at someone’s home.\nSend Alle Invite",
    "appointment_service_id": "030845bb-0b68-4eee-ad4f-09a3b8ce1435",
    "service_id": "d9aa17c2-080c-4747-86df-84962e757150",
    "staff_requested": false,
    "finish_duration": 0,
    "post_client_duration": 0,
    "post_staff_duration": 0,
    "base_appointment_service_id": null,
    "client_message": null,
    "guest_number": 0,
    "hex_color": "",
    "effective_tag_ids": [],
    "editable": false,
    "service_option_ids": null,
    "resource_ids": null,
    "abilities": {
      "cancel": false,
      "edit": false,
      "checkout": true
    },
    "is_new_client": true,
    "booked_by_client_full_name": null,
    "origination": "dashboard",
    "className": "theme-12",
    "durationEditable": false
  },
  {
    "id": "5f0e65a0-f408-4690-a36c-10db39ccc703",
    "start": "2025-10-08T17:15:00-05:00",
    "state": "final",
    "service": {
      "id": "e419e52a-8df0-4514-a690-25c128da759a",
      "name": "PIQo Tattoo",
      "color": 12
    },
    "title": "Hannah Sifuentes",
    "end": "2025-10-08T17:45:00-05:00",
    "duration": 30,
    "price": 200.0,
    "client_id": "86af0fc6-c499-475c-abb4-eab83cf391d5",
    "staff_id": "52598e4f-6524-455a-a06e-96f2489b29ae",
    "recurring_appointment_id": null,
    "notes": "The patient has multiple tattoos and has previously undergone tattoo removal. During her past treatment, she experienced a severe reaction that included blistering and swelling of her arm. She explained that the procedure was performed at a non-credible location. Based on recommendations from friends, she is now seeking treatment in Corpus. The patient resides in Port Lavaca and indicated that evening appointments or Saturdays work best with her schedule. She also mentioned that one of her tattoos was done as a DIY tattoo at someone’s home.\nSend Alle Invite",
    "appointment_service_id": "e5be9855-d7b8-49ae-8f12-64d97d126475",
    "service_id": "e419e52a-8df0-4514-a690-25c128da759a",
    "staff_requested": true,
    "finish_duration": 0,
    "post_client_duration": 0,
    "post_staff_duration": 15,
    "base_appointment_service_id": null,
    "client_message": null,
    "guest_number": 0,
    "hex_color": "",
    "effective_tag_ids": [],
    "editable": false,
    "service_option_ids": null,
    "resource_ids": [
      "e8503e31-e1e9-4f4b-88c4-97d22bf75c16"
    ],
    "abilities": {
      "cancel": false,
      "edit": false,
      "checkout": true
    },
    "is_new_client": true,
    "booked_by_client_full_name": null,
    "origination": "dashboard",
    "className": "theme-12",
    "durationEditable": false
  },
  {
    "id": "694c5af4-c68e-484b-a042-7287cccc4bea",
    "start": "2025-10-13T13:00:00-05:00",
    "state": "final",
    "service": {
      "id": "bf5506da-8fe5-4ea4-9093-c16b4e35ca61",
      "name": "Oceana Diamond",
      "color": 6
    },
    "title": "Sandra Sanders",
    "end": "2025-10-13T15:00:00-05:00",
    "duration": 120,
    "price": 219.0,
    "client_id": "7ad576c1-c152-478e-9432-b55ab61c505f",
    "staff_id": "77b47f65-6c13-43ca-bbba-2aec697935cb",
    "recurring_appointment_id": null,
    "notes": "payment is from karen delinger",
    "appointment_service_id": "b8cd40ad-d128-4bff-95e4-959ae9cc4a13",
    "service_id": "bf5506da-8fe5-4ea4-9093-c16b4e35ca61",
    "staff_requested": true,
    "finish_duration": 0,
    "post_client_duration": 0,
    "post_staff_duration": 15,
    "base_appointment_service_id": null,
    "client_message": null,
    "guest_number": 0,
    "hex_color": "",
    "effective_tag_ids": [],
    "editable": false,
    "service_option_ids": null,
    "resource_ids": null,
    "abilities": {
      "cancel": false,
      "edit": false,
      "checkout": true
    },
    "is_new_client": true,
    "booked_by_client_full_name": null,
    "origination": "dashboard",
    "className": "theme-13",
    "durationEditable": false
  },
  {
    "id": "70771443-57b9-4982-a253-fcc92bab24b1",
    "start": "2025-10-08T17:30:00-05:00",
    "state": "final",
    "service": {
      "id": "039da662-99e3-4e95-8bfc-742b777f73ae",
      "name": "Weight Loss Consultation",
      "color": 8
    },
    "title": "Victoria Escalante",
    "end": "2025-10-08T18:00:00-05:00",
    "duration": 30,
    "price": 100.0,
    "client_id": "684843a3-c08e-4df0-bff2-5e026c687760",
    "staff_id": "b4b9e43d-8e88-4bb7-89e6-c19baad1ccc1",
    "recurring_appointment_id": null,
    "notes": "Interested in the Facebook Weightloss w/Free NAD+ shot\nInterested in: Botox, Dermal Filler, Microneedling & Nad+\n0 Alle Points",
    "appointment_service_id": "c9130fbd-5890-495a-9357-ea1dc63a5eed",
    "service_id": "039da662-99e3-4e95-8bfc-742b777f73ae",
    "staff_requested": false,
    "finish_duration": 0,
    "post_client_duration": 0,
    "post_staff_duration": 15,
    "base_appointment_service_id": null,
    "client_message": null,
    "guest_number": 0,
    "hex_color": "",
    "effective_tag_ids": [],
    "editable": false,
    "service_option_ids": null,
    "resource_ids": null,
    "abilities": {
      "cancel": false,
      "edit": false,
      "checkout": true
    },
    "is_new_client": true,
    "booked_by_client_full_name": null,
    "origination": "dashboard",
    "className": "theme-10",
    "durationEditable": false
  },
  {
    "id": "727eb87b-34e7-4b0c-9905-434e3c25b4dd",
    "start": "2025-10-01T12:30:00-05:00",
    "state": "booked",
    "service": {
      "id": "7b4c15b4-f227-49b4-b3b5-3fee227f4675",
      "name": "Phone Consultation",
      "color": 4
    },
    "title": "RUBEN SALDANA",
    "end": "2025-10-01T12:45:00-05:00",
    "duration": 15,
    "price": 0.0,
    "client_id": "5996c645-9663-444c-8b0d-aa056d5426cd",
    "staff_id": "52598e4f-6524-455a-a06e-96f2489b29ae",
    "recurring_appointment_id": null,
    "notes": "The client has a fresh tattoo, approximately four fingers in length, consisting only of an outline with no color or shading. The tattoo is three days old. He is seeking removal because he plans to replace it with a new design. The client maintains proper tattoo aftercare and specifically does not want a cover-up. However, he is on a tight timeline to have the current tattoo removed so that the new one can be completed.",
    "appointment_service_id": "10d12958-08c7-4ab0-bf1c-2a0e62b0a025",
    "service_id": "7b4c15b4-f227-49b4-b3b5-3fee227f4675",
    "staff_requested": false,
    "finish_duration": 0,
    "post_client_duration": 0,
    "post_staff_duration": 0,
    "base_appointment_service_id": null,
    "client_message": null,
    "guest_number": 0,
    "hex_color": "",
    "effective_tag_ids": [],
    "editable": true,
    "service_option_ids": null,
    "resource_ids": null,
    "abilities": {
      "cancel": true,
      "edit": true,
      "checkout": true
    },
    "is_new_client": true,
    "booked_by_client_full_name": null,
    "origination": "dashboard",
    "className": "theme-12",
    "durationEditable": false
  },
  {
    "id": "77bc8909-1b0b-4814-8360-bb5fee1991b2",
    "start": "2025-10-02T18:00:00-05:00",
    "state": "final",
    "service": {
      "id": "b5ec881b-0040-4457-822f-a34679d03247",
      "name": "Hair Restoration w/PRF Injections",
      "color": 5
    },
    "title": "Reynaldo Saenz",
    "end": "2025-10-02T19:00:00-05:00",
    "duration": 60,
    "price": 233.34,
    "client_id": "05b4aa5a-c440-4263-9d6c-919253d86b68",
    "staff_id": "b4b9e43d-8e88-4bb7-89e6-c19baad1ccc1",
    "recurring_appointment_id": null,
    "notes": null,
    "appointment_service_id": "1adb9a39-0e0e-4e11-b7fe-d57159f3fbcc",
    "service_id": "b5ec881b-0040-4457-822f-a34679d03247",
    "staff_requested": true,
    "finish_duration": 0,
    "post_client_duration": 0,
    "post_staff_duration": 0,
    "base_appointment_service_id": null,
    "client_message": null,
    "guest_number": 0,
    "hex_color": "",
    "effective_tag_ids": [],
    "editable": false,
    "service_option_ids": null,
    "resource_ids": null,
    "abilities": {
      "cancel": false,
      "edit": false,
      "checkout": true
    },
    "is_new_client": true,
    "booked_by_client_full_name": null,
    "origination": "dashboard",
    "className": "theme-10",
    "durationEditable": false
  },
  {
    "id": "784d0cea-509a-43e4-b974-e1c6c85f85ce",
    "start": "2025-10-02T15:00:00-05:00",
    "state": "final",
    "service": {
      "id": "7d097d0f-3aed-463e-a793-23c783efb7a4",
      "name": "CO2 Consultation w/ Visia Skin Analysis",
      "color": 8
    },
    "title": "Shannon Hans",
    "end": "2025-10-02T15:45:00-05:00",
    "duration": 45,
    "price": 65.0,
    "client_id": "9945d2cd-d346-43ac-a687-74224fd25889",
    "staff_id": "77b47f65-6c13-43ca-bbba-2aec697935cb",
    "recurring_appointment_id": null,
    "notes": "Paid deposit\nInterested Co2 eyes and maybe mouth. May be a good candidate for the October Monthly special.",
    "appointment_service_id": "12b355c8-996f-4ec1-9c5d-0d4d19a6a58d",
    "service_id": "7d097d0f-3aed-463e-a793-23c783efb7a4",
    "staff_requested": false,
    "finish_duration": 0,
    "post_client_duration": 0,
    "post_staff_duration": 15,
    "base_appointment_service_id": null,
    "client_message": null,
    "guest_number": 0,
    "hex_color": "",
    "effective_tag_ids": [],
    "editable": false,
    "service_option_ids": null,
    "resource_ids": null,
    "abilities": {
      "cancel": false,
      "edit": false,
      "checkout": true
    },
    "is_new_client": true,
    "booked_by_client_full_name": null,
    "origination": "dashboard",
    "className": "theme-13",
    "durationEditable": false
  },
  {
    "id": "79d0236a-df13-4ea1-959c-79899da29203",
    "start": "2025-10-17T18:15:00-05:00",
    "state": "final",
    "service": {
      "id": "a3f0c51b-e257-49a5-a560-77e6053da938",
      "name": "Neurotoxin (Botox, Dysport)",
      "color": 7
    },
    "title": "Victoria Joslin",
    "end": "2025-10-17T18:45:00-05:00",
    "duration": 30,
    "price": 832.0,
    "client_id": "1405a9f9-aef4-400d-870a-84d98f24da83",
    "staff_id": "b4b9e43d-8e88-4bb7-89e6-c19baad1ccc1",
    "recurring_appointment_id": null,
    "notes": null,
    "appointment_service_id": "4482a9bf-5bdf-4b89-85fc-a4ff3268fa47",
    "service_id": "a3f0c51b-e257-49a5-a560-77e6053da938",
    "staff_requested": true,
    "finish_duration": 0,
    "post_client_duration": 0,
    "post_staff_duration": 0,
    "base_appointment_service_id": null,
    "client_message": null,
    "guest_number": 0,
    "hex_color": "",
    "effective_tag_ids": [],
    "editable": false,
    "service_option_ids": [
      "5f17fe6c-1168-4d2f-9f74-c470fa4c0671"
    ],
    "resource_ids": null,
    "abilities": {
      "cancel": false,
      "edit": false,
      "checkout": true
    },
    "is_new_client": true,
    "booked_by_client_full_name": null,
    "origination": "dashboard",
    "className": "theme-10",
    "durationEditable": false
  },
  {
    "id": "84ec52b5-dcb7-4560-b053-228ed18243d6",
    "start": "2025-10-16T09:15:00-05:00",
    "state": "final",
    "service": {
      "id": "a624749a-4913-4626-a24f-a0baea82bde0",
      "name": "Tattoo Removal",
      "color": 12
    },
    "title": "Harley Davis",
    "end": "2025-10-16T09:45:00-05:00",
    "duration": 30,
    "price": 200.0,
    "client_id": "3b0686c6-c1d3-404a-bc2f-9f77d2e0e2fc",
    "staff_id": "77b47f65-6c13-43ca-bbba-2aec697935cb",
    "recurring_appointment_id": null,
    "notes": "Interested in LHR & Facials",
    "appointment_service_id": "6b640647-bf0e-4316-9653-9c993553229f",
    "service_id": "a624749a-4913-4626-a24f-a0baea82bde0",
    "staff_requested": false,
    "finish_duration": 0,
    "post_client_duration": 0,
    "post_staff_duration": 15,
    "base_appointment_service_id": null,
    "client_message": null,
    "guest_number": 0,
    "hex_color": "",
    "effective_tag_ids": [],
    "editable": false,
    "service_option_ids": null,
    "resource_ids": null,
    "abilities": {
      "cancel": false,
      "edit": false,
      "checkout": true
    },
    "is_new_client": true,
    "booked_by_client_full_name": null,
    "origination": "dashboard",
    "className": "theme-13",
    "durationEditable": false
  },
  {
    "id": "84ec52b5-dcb7-4560-b053-228ed18243d6",
    "start": "2025-10-16T09:00:00-05:00",
    "state": "final",
    "service": {
      "id": "d9aa17c2-080c-4747-86df-84962e757150",
      "name": "Tattoo Removal Consultation",
      "color": 8
    },
    "title": "Harley Davis",
    "end": "2025-10-16T09:15:00-05:00",
    "duration": 15,
    "price": 100.0,
    "client_id": "3b0686c6-c1d3-404a-bc2f-9f77d2e0e2fc",
    "staff_id": "77b47f65-6c13-43ca-bbba-2aec697935cb",
    "recurring_appointment_id": null,
    "notes": "Interested in LHR & Facials",
    "appointment_service_id": "bb83734a-a760-46de-a1c2-0b37fbb8ee6e",
    "service_id": "d9aa17c2-080c-4747-86df-84962e757150",
    "staff_requested": false,
    "finish_duration": 0,
    "post_client_duration": 0,
    "post_staff_duration": 0,
    "base_appointment_service_id": null,
    "client_message": null,
    "guest_number": 0,
    "hex_color": "",
    "effective_tag_ids": [],
    "editable": false,
    "service_option_ids": null,
    "resource_ids": null,
    "abilities": {
      "cancel": false,
      "edit": false,
      "checkout": true
    },
    "is_new_client": true,
    "booked_by_client_full_name": null,
    "origination": "dashboard",
    "className": "theme-13",
    "durationEditable": false
  },
  {
    "id": "8b554533-c015-4194-9258-1edde71fb8d9",
    "start": "2025-10-03T16:00:00-05:00",
    "state": "final",
    "service": {
      "id": "2bc53417-7945-4950-bc8a-bf33621b492c",
      "name": "Dermaplaning",
      "color": 5
    },
    "title": "Diane Lee",
    "end": "2025-10-03T17:00:00-05:00",
    "duration": 60,
    "price": 90.0,
    "client_id": "edd3dd7e-2a43-49e9-bd7d-72c67d60729c",
    "staff_id": "6cf098ff-8414-486b-8465-8ce03cb991a1",
    "recurring_appointment_id": null,
    "notes": null,
    "appointment_service_id": "e018397f-a3f1-44d3-a253-7876ab3f0a55",
    "service_id": "2bc53417-7945-4950-bc8a-bf33621b492c",
    "staff_requested": false,
    "finish_duration": 0,
    "post_client_duration": 0,
    "post_staff_duration": 15,
    "base_appointment_service_id": null,
    "client_message": null,
    "guest_number": 0,
    "hex_color": "",
    "effective_tag_ids": [
      "6c33254d-b2f3-40e1-96bd-4e8cedaad715"
    ],
    "editable": false,
    "service_option_ids": null,
    "resource_ids": null,
    "abilities": {
      "cancel": false,
      "edit": false,
      "checkout": true
    },
    "is_new_client": true,
    "booked_by_client_full_name": null,
    "origination": "sched",
    "className": "theme-1",
    "durationEditable": false
  },
  {
    "id": "978e8f4d-05f0-4d6e-afa6-180b8fbe4193",
    "start": "2025-10-02T11:00:00-05:00",
    "state": "final",
    "service": {
      "id": "2f7bb4b2-9c7e-419a-8a9b-04385306ee23",
      "name": "CoolSculpting Consultation",
      "color": 8
    },
    "title": "celia cross",
    "end": "2025-10-02T12:30:00-05:00",
    "duration": 90,
    "price": 100.0,
    "client_id": "36163dd6-4cb7-4e41-b3c7-e2667f4625df",
    "staff_id": "77b47f65-6c13-43ca-bbba-2aec697935cb",
    "recurring_appointment_id": null,
    "notes": null,
    "appointment_service_id": "b519c962-a9b3-434a-b8ea-ff3a990280ea",
    "service_id": "2f7bb4b2-9c7e-419a-8a9b-04385306ee23",
    "staff_requested": true,
    "finish_duration": 0,
    "post_client_duration": 0,
    "post_staff_duration": 15,
    "base_appointment_service_id": null,
    "client_message": null,
    "guest_number": 0,
    "hex_color": "",
    "effective_tag_ids": [],
    "editable": false,
    "service_option_ids": null,
    "resource_ids": null,
    "abilities": {
      "cancel": false,
      "edit": false,
      "checkout": true
    },
    "is_new_client": true,
    "booked_by_client_full_name": null,
    "origination": "dashboard",
    "className": "theme-13",
    "durationEditable": false
  },
  {
    "id": "98473ea8-4c2d-43c6-842b-a0bf36ba9165",
    "start": "2025-10-22T13:15:00-05:00",
    "state": "confirmed",
    "service": {
      "id": "a3f0c51b-e257-49a5-a560-77e6053da938",
      "name": "Neurotoxin (Botox, Dysport)",
      "color": 7
    },
    "title": "Irina Seitz",
    "end": "2025-10-22T13:45:00-05:00",
    "duration": 30,
    "price": 200.0,
    "client_id": "701f22a8-aa0e-452d-830a-b8123d25c820",
    "staff_id": "b4b9e43d-8e88-4bb7-89e6-c19baad1ccc1",
    "recurring_appointment_id": null,
    "notes": null,
    "appointment_service_id": "0179c6fb-9cfe-40eb-a351-b2116ab22569",
    "service_id": "a3f0c51b-e257-49a5-a560-77e6053da938",
    "staff_requested": true,
    "finish_duration": 0,
    "post_client_duration": 0,
    "post_staff_duration": 15,
    "base_appointment_service_id": null,
    "client_message": null,
    "guest_number": 0,
    "hex_color": "",
    "effective_tag_ids": [],
    "editable": true,
    "service_option_ids": [
      "5f17fe6c-1168-4d2f-9f74-c470fa4c0671"
    ],
    "resource_ids": null,
    "abilities": {
      "cancel": true,
      "edit": true,
      "checkout": true
    },
    "is_new_client": true,
    "booked_by_client_full_name": null,
    "origination": "dashboard",
    "className": "theme-10",
    "durationEditable": false
  },
  {
    "id": "9ef22d04-1e82-4b26-81bc-7e38d5326c42",
    "start": "2025-10-14T18:30:00-05:00",
    "state": "final",
    "service": {
      "id": "e59729c2-1ea8-42d7-ad2b-3b3db748596b",
      "name": "Juvederm Ultra",
      "color": 9
    },
    "title": "Ruby Taylor",
    "end": "2025-10-14T18:30:00-05:00",
    "duration": 0,
    "price": 800.0,
    "client_id": "d550d2dd-bb1c-4190-b6d5-0383b6d33932",
    "staff_id": "b4b9e43d-8e88-4bb7-89e6-c19baad1ccc1",
    "recurring_appointment_id": null,
    "notes": "Wanted more info on the O'shot\nNeeds an Alle invite",
    "appointment_service_id": "29c09a8f-298b-4f3e-b8a3-e63a99616fd3",
    "service_id": "e59729c2-1ea8-42d7-ad2b-3b3db748596b",
    "staff_requested": false,
    "finish_duration": 0,
    "post_client_duration": 0,
    "post_staff_duration": 0,
    "base_appointment_service_id": null,
    "client_message": null,
    "guest_number": 0,
    "hex_color": "",
    "effective_tag_ids": [
      "48e171dc-625e-4bc5-b4af-3586c2bd49e8",
      "95b26d41-99d8-4da3-956d-89522e6c51ed"
    ],
    "editable": false,
    "service_option_ids": null,
    "resource_ids": null,
    "abilities": {
      "cancel": false,
      "edit": false,
      "checkout": true
    },
    "is_new_client": true,
    "booked_by_client_full_name": null,
    "origination": "dashboard",
    "className": "theme-10",
    "durationEditable": false
  },
  {
    "id": "9ef22d04-1e82-4b26-81bc-7e38d5326c42",
    "start": "2025-10-14T18:30:00-05:00",
    "state": "final",
    "service": {
      "id": "a3f0c51b-e257-49a5-a560-77e6053da938",
      "name": "Neurotoxin (Botox, Dysport)",
      "color": 7
    },
    "title": "Ruby Taylor",
    "end": "2025-10-14T19:00:00-05:00",
    "duration": 30,
    "price": 832.0,
    "client_id": "d550d2dd-bb1c-4190-b6d5-0383b6d33932",
    "staff_id": "b4b9e43d-8e88-4bb7-89e6-c19baad1ccc1",
    "recurring_appointment_id": null,
    "notes": "Wanted more info on the O'shot\nNeeds an Alle invite",
    "appointment_service_id": "5bc67f18-6f5d-47f8-bbeb-684aebf37387",
    "service_id": "a3f0c51b-e257-49a5-a560-77e6053da938",
    "staff_requested": true,
    "finish_duration": 0,
    "post_client_duration": 0,
    "post_staff_duration": 15,
    "base_appointment_service_id": null,
    "client_message": null,
    "guest_number": 0,
    "hex_color": "",
    "effective_tag_ids": [
      "48e171dc-625e-4bc5-b4af-3586c2bd49e8",
      "95b26d41-99d8-4da3-956d-89522e6c51ed"
    ],
    "editable": false,
    "service_option_ids": [
      "5f17fe6c-1168-4d2f-9f74-c470fa4c0671"
    ],
    "resource_ids": null,
    "abilities": {
      "cancel": false,
      "edit": false,
      "checkout": true
    },
    "is_new_client": true,
    "booked_by_client_full_name": null,
    "origination": "dashboard",
    "className": "theme-10",
    "durationEditable": false
  },
  {
    "id": "9f5b014f-36ac-4a5f-8166-3c9704694c13",
    "start": "2025-10-18T09:00:00-05:00",
    "state": "final",
    "service": {
      "id": "2bc53417-7945-4950-bc8a-bf33621b492c",
      "name": "Dermaplaning",
      "color": 5
    },
    "title": "Lori Hurtado",
    "end": "2025-10-18T09:00:00-05:00",
    "duration": 0,
    "price": 50.0,
    "client_id": "21c472ae-fd85-4422-8162-0e484519efa6",
    "staff_id": "6cf098ff-8414-486b-8465-8ce03cb991a1",
    "recurring_appointment_id": null,
    "notes": "Monthly service ",
    "appointment_service_id": "7442318e-c944-4359-b48f-411141b618f5",
    "service_id": "2bc53417-7945-4950-bc8a-bf33621b492c",
    "staff_requested": false,
    "finish_duration": 0,
    "post_client_duration": 0,
    "post_staff_duration": 0,
    "base_appointment_service_id": null,
    "client_message": null,
    "guest_number": 0,
    "hex_color": "",
    "effective_tag_ids": [],
    "editable": false,
    "service_option_ids": null,
    "resource_ids": null,
    "abilities": {
      "cancel": false,
      "edit": false,
      "checkout": true
    },
    "is_new_client": true,
    "booked_by_client_full_name": null,
    "origination": "dashboard",
    "className": "theme-1",
    "durationEditable": false
  },
  {
    "id": "9f5b014f-36ac-4a5f-8166-3c9704694c13",
    "start": "2025-10-18T09:00:00-05:00",
    "state": "final",
    "service": {
      "id": "bf5506da-8fe5-4ea4-9093-c16b4e35ca61",
      "name": "Oceana Diamond",
      "color": 6
    },
    "title": "Lori Hurtado",
    "end": "2025-10-18T10:00:00-05:00",
    "duration": 60,
    "price": 219.0,
    "client_id": "21c472ae-fd85-4422-8162-0e484519efa6",
    "staff_id": "6cf098ff-8414-486b-8465-8ce03cb991a1",
    "recurring_appointment_id": null,
    "notes": "Monthly service ",
    "appointment_service_id": "e4b4b05a-16e1-4b0b-b412-8c2a6b3cd0eb",
    "service_id": "bf5506da-8fe5-4ea4-9093-c16b4e35ca61",
    "staff_requested": false,
    "finish_duration": 0,
    "post_client_duration": 0,
    "post_staff_duration": 15,
    "base_appointment_service_id": null,
    "client_message": null,
    "guest_number": 0,
    "hex_color": "",
    "effective_tag_ids": [],
    "editable": false,
    "service_option_ids": null,
    "resource_ids": null,
    "abilities": {
      "cancel": false,
      "edit": false,
      "checkout": true
    },
    "is_new_client": true,
    "booked_by_client_full_name": null,
    "origination": "dashboard",
    "className": "theme-1",
    "durationEditable": false
  },
  {
    "id": "a1099096-8110-422a-9c3b-ecccc75939c4",
    "start": "2025-10-07T18:00:00-05:00",
    "state": "final",
    "service": {
      "id": "01e63b97-3939-4ce7-9d64-532e7474d784",
      "name": "Skin Tag Removal 1-10",
      "color": 10
    },
    "title": "Emmanuel Moncada",
    "end": "2025-10-07T18:30:00-05:00",
    "duration": 30,
    "price": 150.0,
    "client_id": "b80c1714-42c9-4778-acc4-0a1b402ce2b9",
    "staff_id": "b4b9e43d-8e88-4bb7-89e6-c19baad1ccc1",
    "recurring_appointment_id": null,
    "notes": "Booked online\n$105 in credit",
    "appointment_service_id": "c2f20eb5-719c-44ce-aeba-9ac69a21e805",
    "service_id": "01e63b97-3939-4ce7-9d64-532e7474d784",
    "staff_requested": false,
    "finish_duration": 0,
    "post_client_duration": 0,
    "post_staff_duration": 0,
    "base_appointment_service_id": null,
    "client_message": null,
    "guest_number": 0,
    "hex_color": "",
    "effective_tag_ids": [],
    "editable": false,
    "service_option_ids": null,
    "resource_ids": null,
    "abilities": {
      "cancel": false,
      "edit": false,
      "checkout": true
    },
    "is_new_client": true,
    "booked_by_client_full_name": "Emmanuel Moncada",
    "origination": "sched_booking_widget",
    "className": "theme-10",
    "durationEditable": false
  },
  {
    "id": "ab64d84a-a0d1-4b92-ae11-aca58261acec",
    "start": "2025-10-01T16:00:00-05:00",
    "state": "final",
    "service": {
      "id": "d32c4998-ff76-445d-a95e-5ca223005dd6",
      "name": "VISIA - Skin Analysis",
      "color": 8
    },
    "title": "Maria Cantu",
    "end": "2025-10-01T16:45:00-05:00",
    "duration": 45,
    "price": 100.0,
    "client_id": "882216a8-ed90-4024-a201-b08750e91193",
    "staff_id": "6cf098ff-8414-486b-8465-8ce03cb991a1",
    "recurring_appointment_id": null,
    "notes": null,
    "appointment_service_id": "630272a4-da9d-44a6-9953-14929c0eab22",
    "service_id": "d32c4998-ff76-445d-a95e-5ca223005dd6",
    "staff_requested": true,
    "finish_duration": 0,
    "post_client_duration": 0,
    "post_staff_duration": 15,
    "base_appointment_service_id": null,
    "client_message": null,
    "guest_number": 0,
    "hex_color": "",
    "effective_tag_ids": [],
    "editable": false,
    "service_option_ids": null,
    "resource_ids": null,
    "abilities": {
      "cancel": false,
      "edit": false,
      "checkout": true
    },
    "is_new_client": true,
    "booked_by_client_full_name": null,
    "origination": "dashboard",
    "className": "theme-1",
    "durationEditable": false
  },
  {
    "id": "ad369ab7-25f6-4927-8318-804b651dc068",
    "start": "2025-10-02T13:30:00-05:00",
    "state": "final",
    "service": {
      "id": "dea32f03-7e0d-4091-9cd7-cc4d6d1da977",
      "name": "Massage Swedish 90Min",
      "color": 13
    },
    "title": "Tami Spoon",
    "end": "2025-10-02T15:15:00-05:00",
    "duration": 105,
    "price": 125.0,
    "client_id": "f9a2b1ee-64a4-4cd9-98fc-b2cfed8e55c1",
    "staff_id": "bc0900ae-2e0e-4c1a-bc6f-c3dbafb6b508",
    "recurring_appointment_id": null,
    "notes": null,
    "appointment_service_id": "135581f2-c2ef-4d3a-92de-39c57a1496fe",
    "service_id": "dea32f03-7e0d-4091-9cd7-cc4d6d1da977",
    "staff_requested": true,
    "finish_duration": 0,
    "post_client_duration": 0,
    "post_staff_duration": 30,
    "base_appointment_service_id": null,
    "client_message": null,
    "guest_number": 0,
    "hex_color": "",
    "effective_tag_ids": [],
    "editable": false,
    "service_option_ids": null,
    "resource_ids": null,
    "abilities": {
      "cancel": false,
      "edit": false,
      "checkout": true
    },
    "is_new_client": true,
    "booked_by_client_full_name": null,
    "origination": "dashboard",
    "className": "theme-8",
    "durationEditable": false
  },
  {
    "id": "ad369ab7-25f6-4927-8318-804b651dc068",
    "start": "2025-10-02T16:15:00-05:00",
    "state": "final",
    "service": {
      "id": "bf5506da-8fe5-4ea4-9093-c16b4e35ca61",
      "name": "Oceana Diamond",
      "color": 6
    },
    "title": "Tami Spoon",
    "end": "2025-10-02T17:15:00-05:00",
    "duration": 60,
    "price": 300.0,
    "client_id": "f9a2b1ee-64a4-4cd9-98fc-b2cfed8e55c1",
    "staff_id": "6cf098ff-8414-486b-8465-8ce03cb991a1",
    "recurring_appointment_id": null,
    "notes": null,
    "appointment_service_id": "5021f5ff-8a76-4f67-a6e8-d944d3c20420",
    "service_id": "bf5506da-8fe5-4ea4-9093-c16b4e35ca61",
    "staff_requested": false,
    "finish_duration": 0,
    "post_client_duration": 0,
    "post_staff_duration": 15,
    "base_appointment_service_id": null,
    "client_message": null,
    "guest_number": 0,
    "hex_color": "",
    "effective_tag_ids": [],
    "editable": false,
    "service_option_ids": null,
    "resource_ids": null,
    "abilities": {
      "cancel": false,
      "edit": false,
      "checkout": true
    },
    "is_new_client": true,
    "booked_by_client_full_name": null,
    "origination": "dashboard",
    "className": "theme-1",
    "durationEditable": false
  },
  {
    "id": "ae2e2b8e-d708-4d20-814e-c6f38e254cb6",
    "start": "2025-10-16T15:45:00-05:00",
    "state": "arrived",
    "service": {
      "id": "6855fbc5-6e4c-4c4c-8ae2-8caf7ad84c6e",
      "name": "Massage Deep Tissue 60Min",
      "color": 13
    },
    "title": "Willard Hammonds",
    "end": "2025-10-16T16:45:00-05:00",
    "duration": 60,
    "price": 105.0,
    "client_id": "e5bc841b-3f40-474a-9dca-e58ea21eb2f0",
    "staff_id": "bc0900ae-2e0e-4c1a-bc6f-c3dbafb6b508",
    "recurring_appointment_id": null,
    "notes": "referred by Tabitha; for girlfriend EMMIE - paperwork was sent to her email on his acct",
    "appointment_service_id": "41f6816e-5316-4023-9433-516bf3abfe02",
    "service_id": "6855fbc5-6e4c-4c4c-8ae2-8caf7ad84c6e",
    "staff_requested": true,
    "finish_duration": 0,
    "post_client_duration": 0,
    "post_staff_duration": 30,
    "base_appointment_service_id": null,
    "client_message": null,
    "guest_number": 0,
    "hex_color": "",
    "effective_tag_ids": [],
    "editable": true,
    "service_option_ids": null,
    "resource_ids": null,
    "abilities": {
      "cancel": true,
      "edit": true,
      "checkout": true
    },
    "is_new_client": true,
    "booked_by_client_full_name": null,
    "origination": "dashboard",
    "className": "theme-8",
    "durationEditable": false
  },
  {
    "id": "bc78a741-cba6-4476-82ef-40514f46ae1e",
    "start": "2025-10-22T14:00:00-05:00",
    "state": "confirmed",
    "service": {
      "id": "a3f0c51b-e257-49a5-a560-77e6053da938",
      "name": "Neurotoxin (Botox, Dysport)",
      "color": 7
    },
    "title": "Sherry Johnson",
    "end": "2025-10-22T14:30:00-05:00",
    "duration": 30,
    "price": 200.0,
    "client_id": "06f8ad88-05c5-4255-80e1-40db64514d16",
    "staff_id": "b4b9e43d-8e88-4bb7-89e6-c19baad1ccc1",
    "recurring_appointment_id": null,
    "notes": null,
    "appointment_service_id": "96768049-db8c-48b0-b432-b08ffe9c2de6",
    "service_id": "a3f0c51b-e257-49a5-a560-77e6053da938",
    "staff_requested": false,
    "finish_duration": 0,
    "post_client_duration": 0,
    "post_staff_duration": 0,
    "base_appointment_service_id": null,
    "client_message": null,
    "guest_number": 0,
    "hex_color": "",
    "effective_tag_ids": [],
    "editable": true,
    "service_option_ids": [
      "5f17fe6c-1168-4d2f-9f74-c470fa4c0671"
    ],
    "resource_ids": null,
    "abilities": {
      "cancel": true,
      "edit": true,
      "checkout": true
    },
    "is_new_client": true,
    "booked_by_client_full_name": null,
    "origination": "sched",
    "className": "theme-10",
    "durationEditable": false
  },
  {
    "id": "c2b1d823-2aba-4758-810b-317c910a3303",
    "start": "2025-10-22T12:30:00-05:00",
    "state": "confirmed",
    "service": {
      "id": "039da662-99e3-4e95-8bfc-742b777f73ae",
      "name": "Weight Loss Consultation",
      "color": 8
    },
    "title": "Sylvia Garza",
    "end": "2025-10-22T13:00:00-05:00",
    "duration": 30,
    "price": 100.0,
    "client_id": "fc90d0a5-e304-45e8-a362-4aee032e83d9",
    "staff_id": "b4b9e43d-8e88-4bb7-89e6-c19baad1ccc1",
    "recurring_appointment_id": null,
    "notes": null,
    "appointment_service_id": "3f09cb4d-e284-4d98-b9ae-38b53f582e10",
    "service_id": "039da662-99e3-4e95-8bfc-742b777f73ae",
    "staff_requested": false,
    "finish_duration": 0,
    "post_client_duration": 0,
    "post_staff_duration": 15,
    "base_appointment_service_id": null,
    "client_message": null,
    "guest_number": 0,
    "hex_color": "",
    "effective_tag_ids": [],
    "editable": true,
    "service_option_ids": null,
    "resource_ids": null,
    "abilities": {
      "cancel": true,
      "edit": true,
      "checkout": true
    },
    "is_new_client": true,
    "booked_by_client_full_name": null,
    "origination": "dashboard",
    "className": "theme-10",
    "durationEditable": false
  },
  {
    "id": "c4190932-c6bf-4334-8fe2-1f65c682b82b",
    "start": "2025-10-16T13:00:00-05:00",
    "state": "final",
    "service": {
      "id": "ba5010d7-756a-4236-8a75-e0a9eb4a9ba3",
      "name": "Laser Hair Removal Platinum - MEDIUM",
      "color": 4
    },
    "title": "Emily Jennings",
    "end": "2025-10-16T14:00:00-05:00",
    "duration": 60,
    "price": 225.0,
    "client_id": "396bc215-8d6a-4063-bc0d-860378d2f3f9",
    "staff_id": "6cf098ff-8414-486b-8465-8ce03cb991a1",
    "recurring_appointment_id": null,
    "notes": null,
    "appointment_service_id": "5016c71a-5fa8-46f7-9754-620598d3d684",
    "service_id": "ba5010d7-756a-4236-8a75-e0a9eb4a9ba3",
    "staff_requested": true,
    "finish_duration": 0,
    "post_client_duration": 0,
    "post_staff_duration": 15,
    "base_appointment_service_id": null,
    "client_message": null,
    "guest_number": 0,
    "hex_color": "",
    "effective_tag_ids": [],
    "editable": false,
    "service_option_ids": null,
    "resource_ids": null,
    "abilities": {
      "cancel": false,
      "edit": false,
      "checkout": true
    },
    "is_new_client": true,
    "booked_by_client_full_name": null,
    "origination": "dashboard",
    "className": "theme-1",
    "durationEditable": false
  },
  {
    "id": "d8d7c8f7-ddad-483a-bfce-0535e3daa197",
    "start": "2025-10-10T13:15:00-05:00",
    "state": "booked",
    "service": {
      "id": "7b4c15b4-f227-49b4-b3b5-3fee227f4675",
      "name": "Phone Consultation",
      "color": 4
    },
    "title": "Ashley Ruiz",
    "end": "2025-10-10T13:30:00-05:00",
    "duration": 15,
    "price": 0.0,
    "client_id": "d8be0ed0-fa97-43d0-bcbd-1cfcadc0dbcc",
    "staff_id": "b4b9e43d-8e88-4bb7-89e6-c19baad1ccc1",
    "recurring_appointment_id": null,
    "notes": "She has Bell’s Palsy and wants to treat the right side with Botox. I sent her the Allē link, and she said she’ll sign up to check if she’s eligible for the $65 off. I put her on Amanda's Boulevard to call her back at 1:00pm tomorrow.",
    "appointment_service_id": "ba801173-7981-4616-acb3-b343ba0103de",
    "service_id": "7b4c15b4-f227-49b4-b3b5-3fee227f4675",
    "staff_requested": false,
    "finish_duration": 0,
    "post_client_duration": 0,
    "post_staff_duration": 0,
    "base_appointment_service_id": null,
    "client_message": null,
    "guest_number": 0,
    "hex_color": "",
    "effective_tag_ids": [],
    "editable": true,
    "service_option_ids": null,
    "resource_ids": null,
    "abilities": {
      "cancel": true,
      "edit": true,
      "checkout": true
    },
    "is_new_client": true,
    "booked_by_client_full_name": null,
    "origination": "dashboard",
    "className": "theme-10",
    "durationEditable": false
  },
  {
    "id": "dafa0562-a740-47b5-ab25-2f0869188d90",
    "start": "2025-10-02T14:00:00-05:00",
    "state": "final",
    "service": {
      "id": "0adf184b-1afa-426c-8f3b-52742f14ab59",
      "name": "Laser Consultation w/Visia Skin Analysis",
      "color": 8
    },
    "title": "Ethan Atkinson",
    "end": "2025-10-02T14:45:00-05:00",
    "duration": 45,
    "price": 0.0,
    "client_id": "84c36122-94a7-4081-8b98-edecc137e6bb",
    "staff_id": "52598e4f-6524-455a-a06e-96f2489b29ae",
    "recurring_appointment_id": null,
    "notes": null,
    "appointment_service_id": "2fc463b6-251e-4bed-b207-a54b451fd172",
    "service_id": "0adf184b-1afa-426c-8f3b-52742f14ab59",
    "staff_requested": false,
    "finish_duration": 0,
    "post_client_duration": 0,
    "post_staff_duration": 15,
    "base_appointment_service_id": null,
    "client_message": null,
    "guest_number": 0,
    "hex_color": "",
    "effective_tag_ids": [],
    "editable": false,
    "service_option_ids": null,
    "resource_ids": null,
    "abilities": {
      "cancel": false,
      "edit": false,
      "checkout": true
    },
    "is_new_client": true,
    "booked_by_client_full_name": "Ethan Atkinson",
    "origination": "sched_booking_widget",
    "className": "theme-12",
    "durationEditable": false
  },
  {
    "id": "e734acc7-022a-486a-8ef0-5eced165a3ac",
    "start": "2025-10-03T11:00:00-05:00",
    "state": "final",
    "service": {
      "id": "0adf184b-1afa-426c-8f3b-52742f14ab59",
      "name": "Laser Consultation w/Visia Skin Analysis",
      "color": 8
    },
    "title": "Susie Villanueva",
    "end": "2025-10-03T11:45:00-05:00",
    "duration": 45,
    "price": 0.0,
    "client_id": "bf343ed4-186e-4d03-90a4-077b406b3b44",
    "staff_id": "52598e4f-6524-455a-a06e-96f2489b29ae",
    "recurring_appointment_id": null,
    "notes": null,
    "appointment_service_id": "1fe6d0e2-e2c4-4ca2-9650-9c34cce53feb",
    "service_id": "0adf184b-1afa-426c-8f3b-52742f14ab59",
    "staff_requested": false,
    "finish_duration": 0,
    "post_client_duration": 0,
    "post_staff_duration": 15,
    "base_appointment_service_id": null,
    "client_message": null,
    "guest_number": 0,
    "hex_color": "",
    "effective_tag_ids": [],
    "editable": false,
    "service_option_ids": null,
    "resource_ids": null,
    "abilities": {
      "cancel": false,
      "edit": false,
      "checkout": true
    },
    "is_new_client": true,
    "booked_by_client_full_name": null,
    "origination": "dashboard",
    "className": "theme-12",
    "durationEditable": false
  },
  {
    "id": "e734acc7-022a-486a-8ef0-5eced165a3ac",
    "start": "2025-10-03T11:30:00-05:00",
    "state": "final",
    "service": {
      "id": "abe8b73f-dfbc-4650-8631-199418f8325b",
      "name": "Oceana Elite",
      "color": 10
    },
    "title": "Susie Villanueva",
    "end": "2025-10-03T12:30:00-05:00",
    "duration": 60,
    "price": 219.0,
    "client_id": "bf343ed4-186e-4d03-90a4-077b406b3b44",
    "staff_id": "52598e4f-6524-455a-a06e-96f2489b29ae",
    "recurring_appointment_id": null,
    "notes": null,
    "appointment_service_id": "7849de0d-b8eb-4c6f-b3c1-008abad4ac13",
    "service_id": "abe8b73f-dfbc-4650-8631-199418f8325b",
    "staff_requested": true,
    "finish_duration": 0,
    "post_client_duration": 0,
    "post_staff_duration": 15,
    "base_appointment_service_id": null,
    "client_message": null,
    "guest_number": 0,
    "hex_color": "",
    "effective_tag_ids": [],
    "editable": false,
    "service_option_ids": null,
    "resource_ids": null,
    "abilities": {
      "cancel": false,
      "edit": false,
      "checkout": true
    },
    "is_new_client": true,
    "booked_by_client_full_name": null,
    "origination": "dashboard",
    "className": "theme-12",
    "durationEditable": false
  },
  {
    "id": "e734acc7-022a-486a-8ef0-5eced165a3ac",
    "start": "2025-10-03T10:00:00-05:00",
    "state": "final",
    "service": {
      "id": "bb8842be-d143-4e9c-9e0d-2d6106839fdd",
      "name": "Injectable Filler Consultation w/Visia Skin Analysis",
      "color": 8
    },
    "title": "Susie Villanueva",
    "end": "2025-10-03T10:45:00-05:00",
    "duration": 45,
    "price": 100.0,
    "client_id": "bf343ed4-186e-4d03-90a4-077b406b3b44",
    "staff_id": "b4b9e43d-8e88-4bb7-89e6-c19baad1ccc1",
    "recurring_appointment_id": null,
    "notes": null,
    "appointment_service_id": "ec05675d-b4a5-44c1-96c4-f9b786ef1999",
    "service_id": "bb8842be-d143-4e9c-9e0d-2d6106839fdd",
    "staff_requested": true,
    "finish_duration": 0,
    "post_client_duration": 0,
    "post_staff_duration": 0,
    "base_appointment_service_id": null,
    "client_message": null,
    "guest_number": 0,
    "hex_color": "",
    "effective_tag_ids": [],
    "editable": false,
    "service_option_ids": null,
    "resource_ids": null,
    "abilities": {
      "cancel": false,
      "edit": false,
      "checkout": true
    },
    "is_new_client": true,
    "booked_by_client_full_name": null,
    "origination": "dashboard",
    "className": "theme-10",
    "durationEditable": false
  },
  {
    "id": "f01c0127-ff1d-404e-a259-aa486c7e3a2a",
    "start": "2025-10-10T11:00:00-05:00",
    "state": "final",
    "service": {
      "id": "1e6e6554-677f-46f9-9687-89dc7e1e9a06",
      "name": "Oceana Teen",
      "color": 8
    },
    "title": "Annabelle Fuentes",
    "end": "2025-10-10T11:45:00-05:00",
    "duration": 45,
    "price": 150.0,
    "client_id": "4c9883bf-e98e-4fe9-8f4a-962ee8d5f785",
    "staff_id": "52598e4f-6524-455a-a06e-96f2489b29ae",
    "recurring_appointment_id": null,
    "notes": "Seleste will pay for the Teen Facial on 10/10/25 when she checks out.",
    "appointment_service_id": "6a04bae4-53e9-459f-b354-9da913795672",
    "service_id": "1e6e6554-677f-46f9-9687-89dc7e1e9a06",
    "staff_requested": false,
    "finish_duration": 0,
    "post_client_duration": 0,
    "post_staff_duration": 15,
    "base_appointment_service_id": null,
    "client_message": null,
    "guest_number": 0,
    "hex_color": "",
    "effective_tag_ids": [
      "904c787c-9129-410f-b4a0-2c262df61706"
    ],
    "editable": false,
    "service_option_ids": null,
    "resource_ids": null,
    "abilities": {
      "cancel": false,
      "edit": false,
      "checkout": true
    },
    "is_new_client": true,
    "booked_by_client_full_name": null,
    "origination": "dashboard",
    "className": "theme-12",
    "durationEditable": false
  },
  {
    "id": "f7188728-693f-40ac-9aa9-6583d8d6e031",
    "start": "2025-10-01T15:00:00-05:00",
    "state": "final",
    "service": {
      "id": "d32c4998-ff76-445d-a95e-5ca223005dd6",
      "name": "VISIA - Skin Analysis",
      "color": 8
    },
    "title": "Jose Cantu",
    "end": "2025-10-01T15:45:00-05:00",
    "duration": 45,
    "price": 0.0,
    "client_id": "706647e3-ba9f-414c-bf41-2a5e31adb314",
    "staff_id": "6cf098ff-8414-486b-8465-8ce03cb991a1",
    "recurring_appointment_id": null,
    "notes": null,
    "appointment_service_id": "3444db63-1e45-4669-8891-43aa6a6fc21c",
    "service_id": "d32c4998-ff76-445d-a95e-5ca223005dd6",
    "staff_requested": true,
    "finish_duration": 0,
    "post_client_duration": 0,
    "post_staff_duration": 15,
    "base_appointment_service_id": null,
    "client_message": null,
    "guest_number": 0,
    "hex_color": "",
    "effective_tag_ids": [],
    "editable": false,
    "service_option_ids": null,
    "resource_ids": null,
    "abilities": {
      "cancel": false,
      "edit": false,
      "checkout": true
    },
    "is_new_client": true,
    "booked_by_client_full_name": null,
    "origination": "dashboard",
    "className": "theme-1",
    "durationEditable": false
  },
  {
    "id": "f9b9491b-c0f4-48a1-9bbd-2b2fa77137eb",
    "start": "2025-10-17T17:00:00-05:00",
    "state": "final",
    "service": {
      "id": "a3f0c51b-e257-49a5-a560-77e6053da938",
      "name": "Neurotoxin (Botox, Dysport)",
      "color": 7
    },
    "title": "Belinda aka Bella Prather",
    "end": "2025-10-17T17:30:00-05:00",
    "duration": 30,
    "price": 832.0,
    "client_id": "f2052e8f-10cf-4bf7-960b-daac6d3a48d3",
    "staff_id": "b4b9e43d-8e88-4bb7-89e6-c19baad1ccc1",
    "recurring_appointment_id": null,
    "notes": "0 Alle Points",
    "appointment_service_id": "dfb7e971-daf7-45e2-91d1-330403f1a341",
    "service_id": "a3f0c51b-e257-49a5-a560-77e6053da938",
    "staff_requested": true,
    "finish_duration": 0,
    "post_client_duration": 0,
    "post_staff_duration": 0,
    "base_appointment_service_id": null,
    "client_message": null,
    "guest_number": 0,
    "hex_color": "",
    "effective_tag_ids": [],
    "editable": false,
    "service_option_ids": [
      "5f17fe6c-1168-4d2f-9f74-c470fa4c0671"
    ],
    "resource_ids": null,
    "abilities": {
      "cancel": false,
      "edit": false,
      "checkout": true
    },
    "is_new_client": true,
    "booked_by_client_full_name": null,
    "origination": "dashboard",
    "className": "theme-10",
    "durationEditable": false
  },
  {
    "id": "ffa8501d-3147-4931-824f-8aba7fb27923",
    "start": "2025-10-10T14:30:00-05:00",
    "state": "final",
    "service": {
      "id": "d32c4998-ff76-445d-a95e-5ca223005dd6",
      "name": "VISIA - Skin Analysis",
      "color": 8
    },
    "title": "Leslie Gallardo",
    "end": "2025-10-10T15:30:00-05:00",
    "duration": 60,
    "price": 100.0,
    "client_id": "834f2cba-d99e-429d-81d8-a7bb65e89fb7",
    "staff_id": "52598e4f-6524-455a-a06e-96f2489b29ae",
    "recurring_appointment_id": null,
    "notes": null,
    "appointment_service_id": "a1e68087-fd42-498d-89a3-fd470baf564d",
    "service_id": "d32c4998-ff76-445d-a95e-5ca223005dd6",
    "staff_requested": true,
    "finish_duration": 0,
    "post_client_duration": 0,
    "post_staff_duration": 15,
    "base_appointment_service_id": null,
    "client_message": null,
    "guest_number": 0,
    "hex_color": "",
    "effective_tag_ids": [],
    "editable": false,
    "service_option_ids": null,
    "resource_ids": null,
    "abilities": {
      "cancel": false,
      "edit": false,
      "checkout": true
    },
    "is_new_client": true,
    "booked_by_client_full_name": null,
    "origination": "dashboard",
    "className": "theme-12",
    "durationEditable": false
  }
]